iDEA_mod_inversion/__init__.py
iDEA_mod_inversion/interactions.py
iDEA_mod_inversion/observables.py
iDEA_mod_inversion/reverse_engineering.py
iDEA_mod_inversion/setup.py
iDEA_mod_inversion/state.py
iDEA_mod_inversion/system.py
iDEA_mod_inversion/utilities.py
iDEA_mod_inversion/methods/__init__.py
iDEA_mod_inversion/methods/hartree.py
iDEA_mod_inversion/methods/hartree_fock.py
iDEA_mod_inversion/methods/hybrid.py
iDEA_mod_inversion/methods/interacting.py
iDEA_mod_inversion/methods/lda.py
iDEA_mod_inversion/methods/non_interacting.py
idea_mod_inversions-1.1.7.dist-info/METADATA
idea_mod_inversions-1.1.7.dist-info/WHEEL
idea_mod_inversions-1.1.7.dist-info/top_level.txt
idea_mod_inversions-1.1.7.dist-info/RECORD
