Metadata-Version: 2.4
Name: iDEA_mod_inversions
Version: 1.1.7
Summary: modified version of the iDEA code with Wang-Parr inversion method added, for installation on pinnacles
Author-email: "Anthony R. Osborne" <anthony.r.osborne019@pm.me>
License-Expression: MIT
Classifier: Programming Language :: Python :: 3
Classifier: Operating System :: OS Independent
Requires-Python: >=3.9
